powerfactory_utils/__init__.py
powerfactory_utils/constants.py
powerfactory_utils/exporter/__init__.py
powerfactory_utils/exporter/exporter.py
powerfactory_utils/exporter/load_power.py
powerfactory_utils/interface.py
powerfactory_utils/powerfactory_types.py
powerfactory_utils/schema/__init__.py
powerfactory_utils/schema/base.py
powerfactory_utils/schema/steadystate_case/__init__.py
powerfactory_utils/schema/steadystate_case/active_power.py
powerfactory_utils/schema/steadystate_case/case.py
powerfactory_utils/schema/steadystate_case/controller.py
powerfactory_utils/schema/steadystate_case/external_grid.py
powerfactory_utils/schema/steadystate_case/load.py
powerfactory_utils/schema/steadystate_case/reactive_power.py
powerfactory_utils/schema/steadystate_case/transformer.py
powerfactory_utils/schema/topology/__init__.py
powerfactory_utils/schema/topology/active_power.py
powerfactory_utils/schema/topology/branch.py
powerfactory_utils/schema/topology/characteristic.py
powerfactory_utils/schema/topology/coupler.py
powerfactory_utils/schema/topology/external_grid.py
powerfactory_utils/schema/topology/load.py
powerfactory_utils/schema/topology/load_model.py
powerfactory_utils/schema/topology/node.py
powerfactory_utils/schema/topology/reactive_power.py
powerfactory_utils/schema/topology/switch.py
powerfactory_utils/schema/topology/topology.py
powerfactory_utils/schema/topology/transformer.py
powerfactory_utils/schema/topology/windings.py
powerfactory_utils/schema/topology_case/__init__.py
powerfactory_utils/schema/topology_case/case.py
powerfactory_utils/schema/topology_case/element_state.py
powerfactory_utils-1.3.1.dist-info/WHEEL
powerfactory_utils-1.3.1.dist-info/METADATA
powerfactory_utils-1.3.1.dist-info/licenses/LICENSE
powerfactory_utils-1.3.1.dist-info/licenses/AUTHORS.md
powerfactory_utils-1.3.1.dist-info/RECORD
