Metadata-Version: 2.1
Name: powerfactory-utils
Version: 1.3.1
Summary: A toolbox for Python based control of DIgSILENT PowerFactory
Author-email: Sasan Jacob Rasti <sasan_jacob.rasti@tu-dresden.de>,Maximilian Schmidt <maximilian.schmidt@tu-dresden.de>,Sebastian Krahmer <sebastian.krahmer@tu-dresden.de>
Requires-Python: >=3.9,<3.11
Requires-Dist: loguru
Requires-Dist: pydantic
Project-URL: homepage, https://github.com/ieeh-tu-dresden/powerfactory-utils
